lib_browser/__init__.py
lib_browser/__main__.py
lib_browser/browser.py
lib_browser/discord_browser.py
lib_browser/side.py
lib_browser-0.0.0.dist-info/AUTHORS
lib_browser-0.0.0.dist-info/METADATA
lib_browser-0.0.0.dist-info/WHEEL
lib_browser-0.0.0.dist-info/entry_points.txt
lib_browser-0.0.0.dist-info/top_level.txt
lib_browser-0.0.0.dist-info/RECORD
