Metadata-Version: 2.1
Name: lib-browser
Version: 0.0.0
Summary: UNKNOWN
Home-page: https://github.com/jfuruness/lib_browser.git
Author: Justin Furuness
Author-email: jfuruness@gmail.com
License: UNKNOWN
Download-URL: https://github.com/jfuruness/lib_browser.git
Keywords: Furuness,Browser,Wrapper,Selenium Wrapper
Platform: UNKNOWN
Classifier: Environment :: Console
Classifier: Intended Audience :: Developers
Classifier: License :: OSI Approved :: BSD License
Classifier: Programming Language :: Python :: 3
Requires-Dist: pynput
Requires-Dist: selenium
